MANIFEST.in
README.md
config_path.py
setup.cfg
setup.py
trex_conf.egg-info/PKG-INFO
trex_conf.egg-info/SOURCES.txt
trex_conf.egg-info/dependency_links.txt
trex_conf.egg-info/top_level.txt
trexconf/__init__.py
trexconf/conf.py
trexconf/config_util.py
trexconf/program_conf.py
trexconf/data/__init__.py
trexconf/data/action_after_unlock_tier_reward.csv
trexconf/data/admin_permission.csv
trexconf/data/barcode_type.csv
trexconf/data/birthday_reward_giveaway_type.csv
trexconf/data/business_type.csv
trexconf/data/countries.csv
trexconf/data/currency.csv
trexconf/data/entitle_reward_condition.csv
trexconf/data/giveaway_method.csv
trexconf/data/giveaway_system_condition.csv
trexconf/data/invoice_no_generator.csv
trexconf/data/loyalty_package.csv
trexconf/data/loyalty_package_feature.csv
trexconf/data/membership_entitle_qualification_type.csv
trexconf/data/membership_expiration_type.csv
trexconf/data/membership_extend_expiry_date_type.csv
trexconf/data/membership_maintain_qualification_type.csv
trexconf/data/membership_upgrade_expiry_type.csv
trexconf/data/merchant_permission.csv
trexconf/data/pos_package.csv
trexconf/data/product_package.csv
trexconf/data/program_status.csv
trexconf/data/push_notification_content_type.csv
trexconf/data/receipt_footer_data_type.csv
trexconf/data/receipt_header_data_type.csv
trexconf/data/redeem_limit_type.csv
trexconf/data/redeem_reward_format.csv
trexconf/data/redemption_catalogue_status.csv
trexconf/data/reward_base.csv
trexconf/data/reward_base_and_reward_format_mapping.csv
trexconf/data/reward_effective_type.csv
trexconf/data/reward_expiration_type.csv
trexconf/data/reward_format.csv
trexconf/data/reward_use_condition.csv
trexconf/data/voucher_status.csv
trexconf/data/voucher_type.csv
trexconf/data/weekday.csv
trexconf/json/__init__.py
trexconf/json/config_path.py