Metadata-Version: 2.4
Name: trex_conf
Version: 1.7.3
Summary: TRex Configuration package
Home-page: https://bitbucket.org/lokjac/trex-conf
Author: Jack Lok
Author-email: sglok77@gmail.com
Classifier: Programming Language :: Python :: 3
Classifier: License :: OSI Approved :: MIT License
Classifier: Operating System :: OS Independent
Dynamic: author
Dynamic: author-email
Dynamic: classifier
Dynamic: description
Dynamic: description-content-type
Dynamic: home-page
Dynamic: summary
